{
  "category": "اختبار الذكاء والمنطق (IQ)",
  "questions": [
    { "points": 200, "q": "ما هو الرقم المفقود في السلسلة: 2، 4، 8، 16، 32، ...؟", "a": "64 (الضرب في 2)" },
    { "points": 200, "q": "ما هو الرقم المفقود في السلسلة: 1، 4، 9، 16، 25، ...؟", "a": "36 (مربعات الأرقام 1، 2، 3، 4، 5، 6)" },
    { "points": 200, "q": "ما هو الرقم المفقود في السلسلة: 1، 1، 2، 3، 5، 8، 13، ...؟", "a": "21 (متتالية فيبوناتشي: جمع آخر رقمين)" },
    { "points": 200, "q": "إذا كان 5 عمال يستغرقون 5 دقائق لصناعة 5 قطع، فكم دقيقة يستغرق 100 عامل لصناعة 100 قطعة؟", "a": "5 دقائق (كل عامل يصنع قطعة واحدة في 5 دقائق)" },
    { "points": 200, "q": "بعض الأشجار أوراقها خضراء. كل الأشجار نباتات. إذن: بعض النباتات أوراقها خضراء. (صحيح أم خطأ)؟", "a": "صحيح" },
    { "points": 200, "q": "ما هو الرقم المفقود في السلسلة: 100، 90، 81، 73، 66، ...؟", "a": "60 (نطرح 10، ثم 9، ثم 8، ثم 7، ثم 6)" },
    { "points": 200, "q": "يوجد 3 تفاحات، أخذتَ أنت منها تفاحتين. كم تفاحة معك الآن؟", "a": "تفاحتان (لأنك أخذتهما)" },
    { "points": 200, "q": "طبيب أعطاك 3 أقراص وقال لك خذ قرصاً كل نصف ساعة. كم دقيقة تستغرق لتناولها كلها؟", "a": "60 دقيقة (القرص الأول الآن، الثاني بعد 30، الثالث بعد 60)" },
    { "points": 200, "q": "ما هو الرقم المفقود: 3، 6، 12، 24، 48، ...؟", "a": "96" },
    { "points": 200, "q": "إذا كان يوم أمس هو غداً بالنسبة ليوم الأربعاء، فما هو اليوم؟", "a": "الجمعة (غداً للأربعاء هو الخميس، وأمس كان الخميس، إذن اليوم الجمعة)" },
    { "points": 200, "q": "سلسلة الحروف: أ، ج، خ، ز، ... ما هو الحرف التالي؟", "a": "ش (تخطي حرف واحد، ثم حرفين، ثم ثلاثة...)" },
    { "points": 200, "q": "كلمة (مستشفى) بالنسبة لـ (طبيب)، مثل كلمة (مدرسة) بالنسبة لـ ...؟", "a": "معلم" },
    { "points": 200, "q": "ما هو الرقم المفقود: 5، 10، 20، 40، 80، ...؟", "a": "160" },
    { "points": 200, "q": "قسم الرقم 30 على نصف (0.5)، ثم أضف 10. ما هي النتيجة؟", "a": "70 (30 ÷ 0.5 = 60، 60 + 10 = 70)" },
    { "points": 200, "q": "إذا كان الطائر يطير، والسمكة تسبح، فماذا يفعل الثعبان؟", "a": "يزحف" },
    { "points": 200, "q": "أنت تشارك في سباق جري، وتجاوزت الشخص الذي في المركز الثاني. في أي مركز أنت الآن؟", "a": "المركز الثاني (أخذت مكانه)" },
    { "points": 200, "q": "كم شهراً في السنة يحتوي على 28 يوماً؟", "a": "12 شهراً (كل الأشهر تحتوي على 28 يوماً على الأقل)" },
    { "points": 200, "q": "ما هو الرقم المفقود: 2، 3، 5، 7، 11، 13، ...؟", "a": "17 (سلسلة الأعداد الأولية Prime numbers)" },
    { "points": 200, "q": "والد مريم لديه 5 بنات: نانا، نيني، نونو، نونو... ما اسم البنت الخامسة؟", "a": "مريم" },
    { "points": 200, "q": "كل الورود زهور. بعض الزهور حمراء. إذن: كل الورود حمراء. (صحيح أم خطأ)؟", "a": "خطأ (الاستنتاج غير منطقي)" },
    { "points": 200, "q": "ما هو الرقم المفقود: 121، 144، 169، 196، ...؟", "a": "225 (مربعات الأرقام 11، 12، 13، 14، 15)" },
    { "points": 200, "q": "إذا كان (أ) أكبر من (ب)، و(ج) أصغر من (ب)، فأيهم الأصغر؟", "a": "(ج)" },
    { "points": 200, "q": "سلسلة: 2، 5، 10، 17، 26، ... ما الرقم التالي؟", "a": "37 (إضافة 3، 5، 7، 9، 11)" },
    { "points": 200, "q": "أي كلمة لا تنتمي للمجموعة: تفاحة، برتقالة، موزة، جزر، عنب؟", "a": "جزر (لأنه من الخضروات والجذور، والباقي فواكه)" },
    { "points": 200, "q": "إذا قلبنا الرقم 6 ليصبح 9، فما هو الرقم الذي إذا قلبناه يظل كما هو؟", "a": "8 (أو 0)" },
    { "points": 200, "q": "سلسلة: 10، 22، 46، 94، ... ما هو الرقم التالي؟", "a": "190 (الضرب في 2 ثم إضافة 2)" },
    { "points": 200, "q": "أخ وأخت أعمارهم معاً 50 سنة. الأخ يكبر أخته بـ 10 سنوات. كم عمر الأخت؟", "a": "20 سنة (الأخ 30 والأخت 20)" },
    { "points": 200, "q": "قطار كهربائي يتجه من الشمال إلى الجنوب بسرعة 100 كم/ساعة، والرياح تهب من الشرق. في أي اتجاه يطير الدخان؟", "a": "لا يوجد دخان (إنه قطار كهربائي)" },
    { "points": 200, "q": "ما هو الرقم الذي يمثل 10% من 20% من الرقم 500؟", "a": "10 (20% من 500 = 100، و10% من 100 = 10)" },
    { "points": 200, "q": "ما هو الرقم المفقود: 8، 27، 64، 125، ...؟", "a": "216 (مكعبات الأرقام 2، 3، 4، 5، 6)" },
    { "points": 200, "q": "إذا كان A=1، B=2، C=3، فما هي قيمة الكلمة BAD؟", "a": "7 (2+1+4)" },
    { "points": 200, "q": "سلسلة: 3، 4، 7، 12، 19، 28، ...؟", "a": "39 (الفروق: 1، 3، 5، 7، 9، 11)" },
    { "points": 200, "q": "ما هو الرقم المفقود: 1، 2، 6، 24، 120، ...؟", "a": "720 (المضروب Factorials: 1!، 2!، 3!، 4!، 5!، 6!)" },
    { "points": 200, "q": "شيء سعره 100 جنيه، زاد سعره بنسبة 10%، ثم انخفض بنسبة 10%. كم سعره الآن؟", "a": "99 جنيه (زاد لـ 110، ثم نقص 10% من الـ 110 أي 11 جنيه)" },

    { "points": 400, "q": "زنبق الماء يتضاعف حجمه كل يوم في بحيرة. إذا كان يستغرق 48 يوماً ليغطي البحيرة بالكامل، ففي أي يوم يغطي نصفها؟", "a": "اليوم 47 (لأنه يتضاعف في اليوم التالي ليغطيها بالكامل)" },
    { "points": 400, "q": "سعر مضرب وكرة معاً 1.10 دولار. المضرب أغلى من الكرة بـ 1.00 دولار. كم سعر الكرة؟", "a": "0.05 دولار (5 سنتات)، والمضرب 1.05 دولار" },
    { "points": 400, "q": "عمر أب 4 أضعاف عمر ابنه. بعد 20 سنة، سيصبح عمر الأب ضعف عمر ابنه فقط. كم عمر الابن الآن؟", "a": "10 سنوات (الأب 40. بعد 20 سنة الابن 30 والأب 60)" },
    { "points": 400, "q": "سلسلة: 3، 7، 15، 31، 63، ... ما الرقم التالي؟", "a": "127 (الضرب في 2 ثم إضافة 1)" },
    { "points": 400, "q": "قطار طوله 100 متر، يسير بسرعة 100 متر في الثانية. كم يستغرق من الوقت ليعبر نفقاً طوله 100 متر بالكامل؟", "a": "ثانيتان (يجب أن يقطع 200 متر: طول النفق + طول القطار ليخرج منه تماماً)" },
    { "points": 400, "q": "سلسلة: 2، 6، 12، 20، 30، 42، ... ما الرقم التالي؟", "a": "56 (الأرقام هي n² + n)" },
    { "points": 400, "q": "أي كلمة لا تنتمي منطقياً: أكسجين، هيدروجين، نيتروجين، ماء، هيليوم؟", "a": "ماء (لأنه مركب، والباقي عناصر)" },
    { "points": 400, "q": "إذا كان 3 قطط يستغرقون 3 دقائق لاصطياد 3 فئران، فكم دقيقة يستغرق 100 قط لاصطياد 100 فأر؟", "a": "3 دقائق (كل قط يستغرق 3 دقائق لاصطياد فأر واحد)" },
    { "points": 400, "q": "سلسلة: 4، 9، 25، 49، 121، ... ما الرقم التالي؟", "a": "169 (مربعات الأعداد الأولية: 2²، 3²، 5²، 7²، 11²، 13²)" },
    { "points": 400, "q": "يوجد 5 أشخاص في غرفة. إذا قام كل شخص بمصافحة جميع الأشخاص الآخرين مرة واحدة فقط، فكم عدد المصافحات الإجمالي؟", "a": "10 مصافحات (القانون: n(n-1)/2)" },
    { "points": 400, "q": "ما هو الرقم المفقود: 1، 8، 27، 64، ...؟", "a": "125 (مكعبات الأرقام)" },
    { "points": 400, "q": "رجل ينظر إلى صورة ويقول: 'ليس لي إخوة أو أخوات، ولكن والد هذا الرجل في الصورة هو ابن والدي'. من في الصورة؟", "a": "ابنه" },
    { "points": 400, "q": "إذا كان (كل أ هي ب)، و(بعض ب هي ج)، فهل بالضرورة (بعض أ هي ج)؟", "a": "لا (غير ضروري منطقياً)" },
    { "points": 400, "q": "سلسلة: 2، 9، 28، 65، 126، ... ما هو الرقم التالي؟", "a": "217 (المتتالية هي n³ + 1)" },
    { "points": 400, "q": "خزان ماء يملأه الأنبوب الأول في ساعتين، والأنبوب الثاني في 3 ساعات. كم يستغرقان معاً لملء الخزان؟", "a": "ساعة و 12 دقيقة (أو 1.2 ساعة، المعادلة: 1/2 + 1/3 = 5/6، المقلوب 6/5 ساعة)" },
    { "points": 400, "q": "ما هو الرقم الذي إذا ضربته في 4 ثم طرحت منه 6، يساوي نفس الرقم إذا جمعت عليه 6؟", "a": "4 (المعادلة: 4x - 6 = x + 6)" },
    { "points": 400, "q": "سلسلة: 13، 17، 25، 32، 37، 47، ... ما الرقم التالي؟", "a": "58 (إضافة مجموع أرقام العدد نفسه، مثلاً 13 + (1+3) = 17)" },
    { "points": 400, "q": "إذا كان عقرب الساعات يشير للرابعة وعقرب الدقائق يشير للثانية عشرة، فما هي الزاوية الصغرى بينهما؟", "a": "120 درجة (كل ساعة تمثل 30 درجة)" },
    { "points": 400, "q": "ما هو الرقم المفقود: 1، 2، 5، 26، ...؟", "a": "677 (الرقم السابق تربيع + 1)" },
    { "points": 400, "q": "رجل يبلغ من العمر 45 عاماً، وابنه يبلغ 15 عاماً. منذ كم سنة كان عمر الأب 4 أضعاف عمر ابنه؟", "a": "منذ 5 سنوات (الأب كان 40 والابن كان 10)" },
    { "points": 400, "q": "في مزرعة يوجد دجاج وأرانب. إذا كان إجمالي عدد الرؤوس 20 وإجمالي الأرجل 60، فكم عدد الأرانب؟", "a": "10 أرانب (و 10 دجاجات)" },
    { "points": 400, "q": "إذا كان x + y = 10، و x * y = 21، فما هي قيمة x² + y²؟", "a": "58 (المعادلة: (x+y)² - 2xy = 100 - 42 = 58)" },
    { "points": 400, "q": "سلسلة الحروف: Z, X, V, T, R, ... ما الحرف التالي؟", "a": "P (تخطي حرف واحد للخلف في الأبجدية الإنجليزية)" },
    { "points": 400, "q": "صنبور يملأ الحوض في 4 ساعات، وثقب في القاع يفرغه في 6 ساعات. إذا فُتحا معاً، متى يمتلئ الحوض؟", "a": "12 ساعة (1/4 - 1/6 = 1/12)" },
    { "points": 400, "q": "سيارة تسير بسرعة 60 كم/ساعة لتقطع نصف المسافة، وتكمل النصف الثاني بسرعة 40 كم/ساعة. ما هي السرعة المتوسطة للرحلة؟", "a": "48 كم/ساعة (وليست 50، لأن السرعة المتوسطة للمسافات المتساوية = 2xy/(x+y))" },
    { "points": 400, "q": "سلسلة: 2، 3، 8، 27، 112، ... ما الرقم التالي؟", "a": "565 (الضرب في 1، 2، 3، 4، 5 وإضافة 1، 2، 3، 4، 5 بالترتيب)" },
    { "points": 400, "q": "إذا كان 1=5، 2=25، 3=125، 4=625، فماذا يساوي 5؟", "a": "1 (مذكورة في المعطى الأول 1=5)" },
    { "points": 400, "q": "ما هي الكلمة الشاذة منطقياً: بوصلة، ساعة، ميزان، خريطة، تلسكوب؟", "a": "ساعة (لأنها تقيس الزمن، والباقي للاتجاهات والمكان)" },
    { "points": 400, "q": "لدينا مكعب كبير يتكون من 27 مكعباً صغيراً (3×3×3) تم طلاؤه من الخارج باللون الأحمر. كم مكعباً صغيراً لم يُمسه الطلاء إطلاقاً؟", "a": "مكعب واحد فقط (يقع في القلب بالمنتصف)" },
    { "points": 400, "q": "مجموع ثلاثة أعداد صحيحة متتالية يساوي 60. ما هو العدد الأكبر بينهم؟", "a": "21 (الأعداد هي 19، 20، 21)" },
    { "points": 400, "q": "سلسلة: 1، 3، 4، 8، 15، 27، ... ما الرقم التالي؟", "a": "50 (جمع آخر 3 أرقام لإنتاج الرقم الجديد)" },
    { "points": 400, "q": "رجل اشترى حصاناً بـ 60 دولاراً، وباعه بـ 70. ثم اشتراه بـ 80 وباعه بـ 90. كم إجمالي ربحه؟", "a": "20 دولاراً (ربح 10 في الصفقة الأولى، و 10 في الثانية)" },
    { "points": 400, "q": "كم عدد المرات التي يظهر فيها الرقم 9 بين الأرقام 1 و 100؟", "a": "20 مرة (9، 19، 29... 90، 91، 92... 99)" },

    { "points": 600, "q": "سقط حلزون في بئر عمقه 30 متراً. يتسلق نهاراً 3 أمتار وينزلق ليلاً مترين. في أي يوم يصل للقمة؟", "a": "في اليوم 28 (لأنه في نهاية اليوم 28 سيصل للقمة 30 متر ولن ينزلق ليلاً)" },
    { "points": 600, "q": "سلسلة أنماط القراءة (Look-and-Say): 1، 11، 21، 1211، 111221، ... ما هو الرقم التالي؟", "a": "312211 (نقرأ الرقم السابق: ثلاثة 1، اثنان 2، واحد 1)" },
    { "points": 600, "q": "كم مرة ينطبق عقربا الساعة (الساعات والدقائق) على بعضهما تماماً خلال 24 ساعة؟", "a": "22 مرة (لأنهم لا ينطبقان بين 11 و 12 إلا في 12 تماماً)" },
    { "points": 600, "q": "لديك 8 كرات متطابقة شكلاً، إحداها أثقل وزناً من البقية. باستخدام ميزان ذو كفتين، ما هو أقل عدد من الوزنات لمعرفة الكرة الأثقل يقيناً؟", "a": "وزنتان (نقسمهم 3 و 3، وكرتين جانباً)" },
    { "points": 600, "q": "لديك فتيلان يحترق كل منهما بالكامل في ساعة واحدة، ولكنهما يحترقان بسرعات غير منتظمة. كيف تحسب 45 دقيقة بالضبط؟", "a": "أشعل الفتيل الأول من الطرفين، والثاني من طرف واحد. عندما ينتهي الأول (30 دقيقة)، أشعل الطرف الآخر للثاني (سيستغرق 15 دقيقة إضافية)" },
    { "points": 600, "q": "إذا كان 3 أشخاص يستطيعون دهان 3 غرف في 3 ساعات، فكم شخصاً نحتاج لدهان 6 غرف في 6 ساعات؟", "a": "3 أشخاص (سرعة الـ 3 أشخاص هي غرفة واحدة كل ساعة)" },
    { "points": 600, "q": "أنت أمام ثلاثة أبواب: خلف الأول قاتل، خلف الثاني أسد جائع لم يأكل منذ 3 سنوات، وخلف الثالث نار مشتعلة. أي باب تختار لتنجو؟", "a": "الباب الثاني (الأسد مات من الجوع منذ 3 سنوات)" },
    { "points": 600, "q": "مدينة كل سكانها إما 'صادقون دائماً' أو 'كاذبون دائماً'. قابلت رجلاً عند مفترق طرق وسألته سؤالاً واحداً لتعرف الطريق للقرية، ما هو؟", "a": "'إذا سألت شخصاً من القرية الأخرى عن الطريق الصحيح، فماذا سيقول؟' ثم اسلك الطريق المعاكس لإجابته." },
    { "points": 600, "q": "ما هو الرقم المفقود في السلسلة: 0، 1، 10، 2، 100، 3، 1000، 4، ...؟", "a": "10000 (سلسلتان متداخلتان: الأرقام 0,1,2,3,4 ومضاعفات الـ 10)" },
    { "points": 600, "q": "لديك درج يحتوي على 10 جوارب سوداء و 10 بيضاء في غرفة مظلمة تماماً. ما هو أقل عدد تسحبه لضمان حصولك على زوج متطابق؟", "a": "3 جوارب (إما 2 سوداء و1 أبيض، أو العكس، فستضمن زوجاً في الحالتين)" },
    { "points": 600, "q": "مسألة مونتي هول: 3 أبواب، خلف أحدها سيارة وخلف الباقي ماعز. اخترت باباً، ففتح المذيع باباً آخر به ماعز وقال لك: هل تريد تغيير خيارك؟ هل التغيير يزيد فرصك رياضياً؟", "a": "نعم، التغيير يرفع نسبة الفوز من 33% إلى 66%." },
    { "points": 600, "q": "سلسلة: 2، 10، 26، 50، 82، ... ما هو الرقم التالي؟", "a": "122 (المتتالية هي (2n - 1)² + 1، أو الفروق تزيد بمقدار 8 كل مرة)" },
    { "points": 600, "q": "عمر أحمد اليوم يعادل 3 أضعاف عمره منذ 4 سنوات مطروحاً منه 4. كم عمر أحمد؟", "a": "8 سنوات (المعادلة: x = 3(x - 4) - 4)" },
    { "points": 600, "q": "إذا كانت الساعة 3:15، فما هي الزاوية الدقيقة بين عقرب الساعات وعقرب الدقائق؟", "a": "7.5 درجات (عقرب الساعات تحرك ربع المسافة نحو رقم 4)" },
    { "points": 600, "q": "يوجد 100 مصباح مطفأ، مر 100 شخص. الأول ضغط كل المفاتيح، الثاني ضغط كل مضاعفات 2، الثالث كل مضاعفات 3.. ما المصابيح التي ستظل مضاءة في النهاية؟", "a": "المصابيح ذات الأرقام التي لها جذر تربيعي صحيح (المربعات الكاملة 1، 4، 9، 16...)" },
    { "points": 600, "q": "كم عدد الأصفار التي ينتهي بها حاصل ضرب الأرقام من 1 إلى 100 (100!)؟", "a": "24 صفراً (بحساب عدد مضاعفات الـ 5 والـ 25)" },
    { "points": 600, "q": "سلسلة: 5، 25، 61، 113، 181، ... ما هو الرقم التالي؟", "a": "265 (الرقم هو مجموع مربعين متتاليين: 1²+2²، 3²+4²، 5²+6²... التالي 11²+12²)" },
    { "points": 600, "q": "لديك 3 صناديق، الأول يحوي تفاحاً فقط، والثاني برتقالاً فقط، والثالث مختلط. كل الملصقات عليها خاطئة. كم ثمرة تسحب لتصحيح الملصقات؟", "a": "ثمرة واحدة من صندوق 'المختلط' (لأن ملصقه خاطئ، فما يخرج منه هو ما يمثله الصندوق بالكامل)" },
    { "points": 600, "q": "متتالية رياضية: 7، 10، 8، 11، 9، 12، ... ما الرقم التالي؟", "a": "10 (النمط: إضافة 3، ثم طرح 2)" },
    { "points": 600, "q": "إذا استغرقت 10 ثوانٍ لقطع جذع شجرة إلى 5 قطع، فكم ثانية تستغرق لقطعه إلى 10 قطع (بنفس السرعة)؟", "a": "22.5 ثانية (لتحصل على 5 قطع تقوم بـ 4 قطعات، كل قطعة 2.5 ثانية. الـ 10 قطع تحتاج 9 قطعات)" },
    { "points": 600, "q": "لغز آينشتاين (مبسط): الإنجليزي يعيش في البيت الأحمر، الإسباني يربي كلباً، القهوة تُشرب في البيت الأخضر. هل يمكن للبريطاني شرب القهوة؟", "a": "لا، لأن القهوة في البيت الأخضر وهو يعيش في الأحمر." },
    { "points": 600, "q": "محيط مربع ومحيط دائرة متساويان. أيهما يمتلك مساحة أكبر؟", "a": "الدائرة" },
    { "points": 600, "q": "متتالية الحروف (بالإنجليزية): O, T, T, F, F, S, S, E, N, ... ما الحرف التالي؟", "a": "T (الحرف الأول من الأرقام بالإنجليزية One, Two, Three... التالي Ten)" },
    { "points": 600, "q": "لدينا 9 نقاط مرتبة في شكل مربع 3x3. كم خطاً مستقيماً متصلاً تحتاج لتوصيل جميع النقاط دون رفع القلم؟", "a": "4 خطوط مستقيمة (بالخروج عن حدود المربع الوهمي)" },
    { "points": 600, "q": "ما هو الرقم الذي إذا قسمته على 2 كان الباقي 1، وعلى 3 الباقي 2، وعلى 4 الباقي 3، وعلى 5 الباقي 4، وعلى 6 الباقي 5، ويقبل القسمة على 7؟", "a": "119" },
    { "points": 600, "q": "صندوق يحتوي على بكتيريا تتضاعف كل دقيقة. يمتلئ في ساعة. إذا بدأنا ببكتيريتين بدلاً من واحدة، متى يمتلئ؟", "a": "59 دقيقة" },
    { "points": 600, "q": "متتالية الأرقام: 2، 12، 36، 80، 150، ... ما الرقم التالي؟", "a": "252 (القاعدة هي n² + n³)" },
    { "points": 600, "q": "سبيكة ذهبية يجب تقسيمها إلى 7 أجزاء متساوية لدفع أجرة عامل يومياً. ما هو أقل عدد من القطع التي يجب قص السبيكة لها؟", "a": "قطعتان (للحصول على أجزاء بحجم 1، 2، و 4، لنتمكن من تكوين أي رقم من 1 لـ 7)" },
    { "points": 600, "q": "يوجد 4 أشخاص يجب أن يعبروا جسراً مظلماً معهم مصباح واحد يكفي لـ 12 دقيقة. سرعاتهم (1، 2، 4، 5) دقائق. كيف يعبرون؟", "a": "يعبر (1,2) يأخذان 2، يعود 1. يعبر (4,5) يأخذان 5، يعود 2. يعبر (1,2) يأخذان 2. المجموع = 2+1+5+2+2 = 12 دقيقة." },
    { "points": 600, "q": "ما هي احتمالية أن يكون لطفل عشوائي في عائلة مكونة من طفلين أخ ذكر، إذا علمنا أن أحدهما ذكر؟", "a": "33.3% أو 1/3 (الاحتمالات المتبقية: ذكر/أنثى، أنثى/ذكر، ذكر/ذكر)" },
    { "points": 600, "q": "ما هو ناتج ضرب: (x-a)(x-b)(x-c)... وصولاً إلى (x-z)؟", "a": "صفر (لأن القوس (x-x) موجود بينهم ويساوي صفراً)" },
    { "points": 600, "q": "إذا كانت احتمالية هطول المطر يوم السبت 50%، ويوم الأحد 50%، فما احتمالية هطول المطر خلال عطلة نهاية الأسبوع (على الأقل في أحد اليومين)؟", "a": "75% (الاحتمال العكسي لعدم الهطول هو 50% × 50% = 25%، إذن الهطول 100 - 25 = 75%)" },
    { "points": 600, "q": "شخص في غرفة مربعة نوافذها الأربعة تطل على الجنوب. مر أمامه دب. ما لون الدب؟", "a": "أبيض (الغرفة الوحيدة التي تطل نوافذها على الجنوب فقط تقع في القطب الشمالي، فالدب قطبي)" }
  ]
}
